cryptg/__init__.py
telethon_pyaesni-0.0.1.dist-info/LICENSE
telethon_pyaesni-0.0.1.dist-info/METADATA
telethon_pyaesni-0.0.1.dist-info/WHEEL
telethon_pyaesni-0.0.1.dist-info/top_level.txt
telethon_pyaesni-0.0.1.dist-info/RECORD
