Metadata-Version: 2.1
Name: telethon-pyaesni
Version: 0.0.1
Summary: telethon bindings for the pyaesni module
Home-page: https://github.com/djsmax/telethon-pyaesni
Author: djsmax
Author-email: max746542@gmail.com
License: MIT License
Keywords: telethon pyaesni
Classifier: Development Status :: 4 - Beta
Classifier: License :: OSI Approved :: MIT License
Classifier: Programming Language :: Python
Classifier: Programming Language :: Python :: 3
Classifier: Programming Language :: Python :: 3.6
Classifier: Programming Language :: Python :: 3.7
Classifier: Programming Language :: Python :: 3.8
Classifier: Programming Language :: Python :: 3.9
Requires-Python: >=3.6
License-File: LICENSE
Requires-Dist: pyaesni
